libera_utils/__init__.py
libera_utils/aws/__init__.py
libera_utils/aws/constants.py
libera_utils/aws/ecr_upload.py
libera_utils/aws/processing_step_function_trigger.py
libera_utils/aws/s3_utilities.py
libera_utils/aws/utils.py
libera_utils/cli.py
libera_utils/config.py
libera_utils/constants.py
libera_utils/data/config.json
libera_utils/data/icie_xtce_tlm.xml
libera_utils/data/jpss1_geolocation_xtce_v1.xml
libera_utils/data/l1a_processing_configs.yml
libera_utils/data/libera_dimensions.yml
libera_utils/data/product_definitions/icie_axis_sample_l1a.yml
libera_utils/data/product_definitions/icie_crit_hk_l1a.yml
libera_utils/data/product_definitions/icie_nom_hk_l1a.yml
libera_utils/data/product_definitions/icie_rad_sample_l1a.yml
libera_utils/data/product_definitions/icie_temp_hk_l1a.yml
libera_utils/data/product_definitions/icie_wfov_sci_l1a.yml
libera_utils/data/product_definitions/jpss_sc_pos_l1a.yml
libera_utils/data/scene_definitions/erbe.csv
libera_utils/data/scene_definitions/trmm.csv
libera_utils/data/spice/jpss4/jpss4_sc_v01.attitude.ck.json
libera_utils/data/spice/jpss4/jpss4_sc_v01.ephemeris.spk.json
libera_utils/data/spice/jpss4/jpss4_v01.fakeclock.sclk.tsc
libera_utils/data/spice/jpss4/libera_az_v01.attitude.ck.json
libera_utils/data/spice/jpss4/libera_az_v01.fixed_offset.spk.json
libera_utils/data/spice/jpss4/libera_base_v01.fixed_offset.spk.json
libera_utils/data/spice/jpss4/libera_el_v01.attitude.ck.json
libera_utils/data/spice/jpss4/libera_el_v01.fixed_offset.spk.json
libera_utils/data/spice/jpss4/libera_lw_rad_v01.fixed_offset.spk.json
libera_utils/data/spice/jpss4/libera_ssw_rad_v01.fixed_offset.spk.json
libera_utils/data/spice/jpss4/libera_sw_rad_v01.fixed_offset.spk.json
libera_utils/data/spice/jpss4/libera_tot_rad_v01.fixed_offset.spk.json
libera_utils/data/spice/jpss4/libera_v01.frames.fk.tf
libera_utils/data/spice/jpss4/libera_v01.instruments.ik.ti
libera_utils/data/spice/jpss4/libera_v01.kernels.tm.json
libera_utils-5.4.3.dist-info/METADATA
libera_utils-5.4.3.dist-info/WHEEL
libera_utils-5.4.3.dist-info/entry_points.txt
libera_utils-5.4.3.dist-info/licenses/LICENSE.txt
libera_utils-5.4.3.dist-info/RECORD
