Metadata-Version: 2.4
Name: libera_utils
Version: 5.4.3
Summary: Utility package for Libera Science Data Processing and the Libera Science Data Center. Copyright 2022 University of Colorado.
License: BSD-3-Clause
License-File: LICENSE.txt
Keywords: libera,earth science,radiation budget,lasp,university of colorado
Author: Stephane Beland
Maintainer: Gavin Medley
Requires-Python: >=3.11,<4
Classifier: Development Status :: 3 - Alpha
Classifier: Intended Audience :: Science/Research
Classifier: Intended Audience :: Developers
Classifier: Topic :: Scientific/Engineering
Classifier: Topic :: Software Development :: Libraries :: Python Modules
Classifier: Programming Language :: Python :: 3
Classifier: Operating System :: OS Independent
Classifier: License :: OSI Approved :: BSD License
Requires-Dist: botocore
Requires-Dist: cloudpathlib[s3] (>=0.14.0,<1.0)
Requires-Dist: docker (>=7.1.0,<8)
Requires-Dist: h5netcdf (>=1.0.0,<2.0.0)
Requires-Dist: importlib-metadata (>=4.8.1,<5)
Requires-Dist: lasp-curryer (>=0.2.0)
Requires-Dist: netCDF4 (>=1.7.0,!=1.7.3,<2.0.0)
Requires-Dist: numpy (>=1.21)
Requires-Dist: pandas (>=2.3.2,<3.0.0)
Requires-Dist: pydantic (>2.0.3)
Requires-Dist: python-ulid (>=2.4.0,<3)
Requires-Dist: pyyaml (>=6.0.2,<7)
Requires-Dist: requests (>=2.27.0,<3.0)
Requires-Dist: setuptools (>=69.0.0)
Requires-Dist: space-packet-parser (==6.0.0)
Requires-Dist: spiceypy (>=5.0.0)
Requires-Dist: urllib3 (<2.0)
Requires-Dist: watchtower (>=3.0.0,<4.0)
Requires-Dist: xarray (>=2023.1.0)
Project-URL: Documentation, https://libera-utils.readthedocs.io
